xsget/__init__.py
xsget/arg_parser.py
xsget/book.py
xsget/chapter.py
xsget/config.py
xsget/xsget.py
xsget/xstxt.py
xsget-0.1.75.dist-info/licenses/LICENSE.md
xsget-0.1.75.dist-info/METADATA
xsget-0.1.75.dist-info/WHEEL
xsget-0.1.75.dist-info/entry_points.txt
xsget-0.1.75.dist-info/top_level.txt
xsget-0.1.75.dist-info/RECORD
