Metadata-Version: 2.4
Name: xsget
Version: 0.1.75
Summary: Console tools to download online novel and convert to text file
Author-email: "Kian-Meng, Ang" <kianmeng@cpan.org>
License-Expression: AGPL-3.0-or-later
Project-URL: Changelog, https://github.com/kianmeng/xsget/blob/master/CHANGELOG.md
Project-URL: Issues, https://github.com/kianmeng/xsget/issues
Project-URL: Source, https://github.com/kianmeng/xsget
Classifier: Development Status :: 4 - Beta
Classifier: Environment :: Console
Classifier: Natural Language :: Chinese (Simplified)
Classifier: Natural Language :: Chinese (Traditional)
Classifier: Programming Language :: Python :: 3 :: Only
Classifier: Programming Language :: Python :: 3.10
Classifier: Programming Language :: Python :: 3.11
Classifier: Programming Language :: Python :: 3.12
Classifier: Programming Language :: Python :: 3.13
Classifier: Programming Language :: Python :: 3.14
Classifier: Programming Language :: Python
Classifier: Topic :: Text Processing :: Filters
Classifier: Topic :: Text Processing :: General
Classifier: Topic :: Text Processing :: Markup :: HTML
Classifier: Topic :: Text Processing
Requires-Python: >=3.10
License-File: LICENSE.md
Requires-Dist: aiofiles
Requires-Dist: aiohttp
Requires-Dist: bs4
Requires-Dist: cssselect
Requires-Dist: lxml
Requires-Dist: natsort
Requires-Dist: playwright
Requires-Dist: regex
Requires-Dist: tomlkit
Requires-Dist: user_agent
Requires-Dist: watchdog
Provides-Extra: test
Requires-Dist: aioresponses; extra == "test"
Requires-Dist: pytest; extra == "test"
Requires-Dist: pytest-asyncio; extra == "test"
Requires-Dist: pytest-cov; extra == "test"
Requires-Dist: pytest-mock; extra == "test"
Requires-Dist: pytest-randomly; extra == "test"
Requires-Dist: pytest-xdist; extra == "test"
Requires-Dist: scripttest; extra == "test"
Provides-Extra: doc
Requires-Dist: furo; extra == "doc"
Requires-Dist: myst-parser; extra == "doc"
Requires-Dist: sphinx; extra == "doc"
Requires-Dist: sphinx-autobuild; extra == "doc"
Requires-Dist: sphinx-autodoc-typehints; extra == "doc"
Requires-Dist: sphinx-copybutton; extra == "doc"
Provides-Extra: pot
Requires-Dist: Babel; extra == "pot"
Provides-Extra: lint
Requires-Dist: mypy; extra == "lint"
Requires-Dist: pre-commit; extra == "lint"
Requires-Dist: ruff; extra == "lint"
Requires-Dist: types-aiofiles; extra == "lint"
Requires-Dist: types-regex; extra == "lint"
Requires-Dist: lxml-stubs; extra == "lint"
Dynamic: license-file
